<?xml version="1.0" encoding="UTF-8"?>
<?xml-stylesheet type="text/xsl" href="ttss.xsl"?>

<timetable>
<option combined="1" totalweeks="0" showemptydays="1" dayclass="reverse">
<link href="m4464.xml" class="xml">Printable HTML version</link>
<weeks>Weeks</weeks>
<dates>Dates</dates>
<week>Week</week>
<date>Date</date>
<all>All weeks</all>
<notes>Notes</notes>
<id>ID</id>
<eventname>Event name</eventname>
<selectwk>Select week</selectwk>
<day>Day</day>
<timeevent>Time / Event</timeevent>
<weekind>Week(s)</weekind>
<details>Details</details>
<custom1>Custom 1</custom1>
<custom2>Panopto</custom2>
<custom3>Published Notes</custom3>
<footer>Published 25/10/2018 16:02:39 - Imperial College London<br />Created by 
<a href="http://www.celcat.com" target="_parent">CELCAT Web Publisher</a></footer>
<subheading>Module timetable - CO240 Models of Computation</subheading></option>
<property />
<span rawix="1" rawlen="52">
<description>Weeks P1-39, 02/07/2018 - 24/06/2019</description>
<title>P1-39</title>
<alleventweeks>YYYYYYYYYYYYYYYYYYYYYYYYYYYYYYYYYYYYYYYYYYYYYYYYYYYY</alleventweeks>
<day id="0">
<name>Monday</name></day>
<day id="1">
<name>Tuesday</name></day>
<day id="2">
<name>Wednesday</name></day>
<day id="3">
<name>Thursday</name></day>
<day id="4">
<name>Friday</name></day></span>
<event id="1286021" timesort="09001100" colour="FFFFBF" date="08/10/2018 - 03/12/2018">
<day>2</day>
<prettytimes>09:00-11:00 Lecture</prettytimes>
<starttime>09:00</starttime>
<endtime>11:00</endtime>
<category>Lecture</category>
<prettyweeks></prettyweeks>
<rawweeks>NNNNNNNNNNNNNNYYYYYYYYYNNNNNNNNNNNNNNNNNNNNNNNNNNNNN</rawweeks>
<resources>
<group title="Groups">
<item>CO-BEng/MEng Computing Year 2 (2)</item>
<item>CO-BEng/MEng Joint Maths &amp; Computing Year 2</item>
<item>CO-BEng/MEng Joint Maths &amp; Computing Year 3</item></group>
<staff title="Staff">
<item>Gardner, Philippa A</item></staff>
<room title="Room">
<item>HXLY 308</item></room>
<module title="Module">
<item>CO240 Models of Computation</item></module></resources>
<eventname>CO240 Models of Computation</eventname></event>
<event id="1286020" timesort="12001300" colour="FFFFBF" date="08/10/2018 - 03/12/2018">
<day>3</day>
<prettytimes>12:00-13:00 Lecture</prettytimes>
<starttime>12:00</starttime>
<endtime>13:00</endtime>
<category>Lecture</category>
<prettyweeks></prettyweeks>
<rawweeks>NNNNNNNNNNNNNNYYYYYYYYYNNNNNNNNNNNNNNNNNNNNNNNNNNNNN</rawweeks>
<resources>
<group title="Groups">
<item>CO-BEng/MEng Computing Year 2 (2)</item>
<item>CO-BEng/MEng Joint Maths &amp; Computing Year 2</item>
<item>CO-BEng/MEng Joint Maths &amp; Computing Year 3</item></group>
<staff title="Staff">
<item>Gardner, Philippa A</item></staff>
<room title="Room">
<item>HXLY 311</item></room>
<module title="Module">
<item>CO240 Models of Computation</item></module></resources>
<eventname>CO240 Models of Computation</eventname></event></timetable>